{"_id":{"$oid":"5b144231689866827401f009"},"ref":"1","atividade":"cinema"}
{"_id":{"$oid":"5b144231689866827401f00b"},"ref":"2","atividade":"circo"}
{"_id":{"$oid":"5b144231689866827401f00d"},"ref":"3","atividade":"dança"}
{"_id":{"$oid":"5b144231689866827401f00f"},"ref":"4","atividade":"música"}
{"_id":{"$oid":"5b144231689866827401f011"},"ref":"5","atividade":"tauromaquia"}
{"_id":{"$oid":"5b144231689866827401f013"},"ref":"6","atividade":"teatro"}
{"_id":{"$oid":"5b14424a6898668274020b93"},"ref":"1","atividade":"cinema"}
{"_id":{"$oid":"5b14424a6898668274020b95"},"ref":"2","atividade":"circo"}
{"_id":{"$oid":"5b14424a6898668274020b97"},"ref":"3","atividade":"dança"}
{"_id":{"$oid":"5b14424a6898668274020b99"},"ref":"4","atividade":"música"}
{"_id":{"$oid":"5b14424a6898668274020b9b"},"ref":"5","atividade":"tauromaquia"}
{"_id":{"$oid":"5b14424a6898668274020b9d"},"ref":"6","atividade":"teatro"}
{"_id":{"$oid":"5b14432d6898668274022744"},"ref":"1","atividade":"cinema"}
{"_id":{"$oid":"5b14432d6898668274022746"},"ref":"2","atividade":"circo"}
{"_id":{"$oid":"5b14432d6898668274022748"},"ref":"3","atividade":"dança"}
{"_id":{"$oid":"5b14432d689866827402274a"},"ref":"4","atividade":"música"}
{"_id":{"$oid":"5b14432d689866827402274c"},"ref":"5","atividade":"tauromaquia"}
{"_id":{"$oid":"5b14432d689866827402274e"},"ref":"6","atividade":"teatro"}
{"_id":{"$oid":"5b14435868986682740242ca"},"ref":"1","atividade":"cinema"}
{"_id":{"$oid":"5b14435868986682740242cc"},"ref":"2","atividade":"circo"}
{"_id":{"$oid":"5b14435868986682740242ce"},"ref":"3","atividade":"dança"}
{"_id":{"$oid":"5b14435868986682740242d0"},"ref":"4","atividade":"música"}
{"_id":{"$oid":"5b14435868986682740242d2"},"ref":"5","atividade":"tauromaquia"}
{"_id":{"$oid":"5b14435868986682740242d4"},"ref":"6","atividade":"teatro"}
